age_simple_sql/AGESimpleSQL.py
age_simple_sql/__init__.py
age_simple_sql/models.py
age_simple_sql/utils.py
age_simple_sql-0.3.3.dist-info/LICENSE
age_simple_sql-0.3.3.dist-info/METADATA
age_simple_sql-0.3.3.dist-info/WHEEL
age_simple_sql-0.3.3.dist-info/top_level.txt
age_simple_sql-0.3.3.dist-info/RECORD
