Metadata-Version: 2.1
Name: age_simple_sql
Version: 0.3.3
Summary: A simple SQL wrapper for Apache AGE using psycopg2 connection pooling.
Home-page: https://github.com/MatheusFarias03/AGESimpleSQL
Author: Matheus Farias de Oliveira Matsumoto
License-File: LICENSE
Requires-Dist: psycopg2-binary
